{
  "address": {
    "full": "1234 NW 23rd Avenue, Portland, OR 97210",
    "house_number": "1234",
    "street": "Northwest 23rd Avenue",
    "neighborhood": "Nob Hill",
    "suburb": "Northwest District",
    "city": "Portland",
    "county": "Multnomah County",
    "state": "Oregon",
    "postcode": "97210",
    "country": "United States",
    "coordinates": {
      "latitude": 45.5317783,
      "longitude": -122.6985663
    },
    "osm_type": "way",
    "osm_id": "119636244",
    "display_name": "1234, Northwest 23rd Avenue, Nob Hill, Northwest District, Portland, Multnomah County, Oregon, 97210, United States"
  },
  "timestamp": "2026-07-15",
  "walkability": {
    "overall_score": 10,
    "overall_rating": "Walker's Paradise",
    "description": "Daily errands do not require a car. This is a prime walkable urban location.",
    "breakdown": {
      "walk_score": { "score": 10, "rating": "Walker's Paradise" },
      "transit_score": { "score": 9.4, "rating": "Excellent", "details": "8 transit stops within 1km; nearest stop 128m away (NW 23rd & Marshall)" },
      "bike_score": { "score": 9, "rating": "Very Bikeable", "details": "Bike shop (Cyclepath West) within 900m; Portland bike-friendly infrastructure" },
      "groceries": {
        "score": 7.1,
        "rating": "Good",
        "count_within_1km": 3,
        "avg_distance_m": 668,
        "nearest": { "name": "Lovejoy Grocery", "distance_m": 173.3, "address": "1025 NW 23rd Ave" },
        "options": [
          { "name": "Lovejoy Grocery", "distance_m": 173.3, "address": "1025 NW 23rd Ave", "type": "convenience", "hours": "N/A" },
          { "name": "Natural Mart #3", "distance_m": 875.6, "address": "522 NW 19th Ave", "type": "convenience", "hours": "Mo-Sa 08:00-23:00; Su 09:00-22:00" },
          { "name": "Zupan's", "distance_m": 955.4, "address": "2340 W Burnside St", "type": "supermarket", "hours": "Mo-Su 06:00-22:00" }
        ]
      },
      "restaurants": {
        "score": 9.8,
        "rating": "Excellent",
        "count_within_1km": 89,
        "avg_distance_m": 543,
        "nearest": { "name": "Tara Thai Northwest", "distance_m": 42.2 },
        "cuisine_diversity": ["Thai", "Lao", "Burmese", "Indian", "Greek", "Mexican", "Italian", "Vietnamese", "Korean", "Latin", "American"],
        "nearest_sample": [
          { "name": "Tara Thai Northwest", "distance_m": 42.2, "cuisine": "Thai/Lao", "address": "1310 NW 23rd Ave" },
          { "name": "Top Burmese Burma Joy", "distance_m": 46.8, "cuisine": "Burmese/Asian", "address": "1305 NW 23rd Ave" },
          { "name": "Siri Indian Cuisine", "distance_m": 68.6, "cuisine": "Indian", "address": "1323 NW 23rd Ave" },
          { "name": "Henry Higgins Boiled Bagels", "distance_m": 95, "cuisine": "Bagel/American", "address": "1308 NW 23rd Ave" },
          { "name": "Pepino's", "distance_m": 98, "cuisine": "Mexican", "address": "1036 NW 23rd Ave" },
          { "name": "Case Study Coffee Roasters", "distance_m": 114, "cuisine": "Cafe", "address": "1400 NW 23rd Ave" },
          { "name": "Palomar", "distance_m": 143, "cuisine": "Latin/British", "address": "1422 NW 23rd Ave" },
          { "name": "Dorio Greek Taverna", "distance_m": 158, "cuisine": "Greek", "address": "1037 NW 23rd Ave" },
          { "name": "Matador", "distance_m": 163, "cuisine": "Mexican", "address": "1438 NW 23rd Ave" },
          { "name": "Grassa", "distance_m": 188, "cuisine": "Italian", "address": "1506 NW 23rd Ave" },
          { "name": "Bibi 2 Go", "distance_m": 181, "cuisine": "Korean", "address": "1019 NW 23rd Ave" },
          { "name": "Hem 23 Vietnamese Bar & Grill", "distance_m": 207, "cuisine": "Vietnamese", "address": "1514 NW 23rd Ave" }
        ]
      },
      "healthcare": {
        "score": 9.8,
        "rating": "Excellent",
        "count_within_1km": 6,
        "avg_distance_m": 674,
        "nearest": { "name": "Walgreens Pharmacy", "distance_m": 38.1, "address": "1215 NW 23rd Ave" },
        "options": [
          { "name": "Walgreens Pharmacy", "distance_m": 38.1, "address": "1215 NW 23rd Ave", "hours": "Mo-Fr 08:30-18:00" },
          { "name": "Integrative Primary Care Associates", "distance_m": 452.7, "address": "2050 NW Lovejoy St", "type": "doctor" },
          { "name": "James P. Thomas, MD", "distance_m": 727.6, "address": "909 NW 18th Ave", "type": "doctor (ENT)" },
          { "name": "Walgreens Pharmacy", "distance_m": 918.3, "address": "2103 W Burnside St", "hours": "Mo-Fr 08:00-22:00; Sa 09:00-18:00; Su 10:00-18:00" },
          { "name": "Fred Meyer Pharmacy", "distance_m": 922.7, "address": "100 NW 20th Place", "hours": "Mo-Fr 09:00-20:00; Sa 09:00-18:00; Su 10:00-17:00" },
          { "name": "Portland Dermatology Clinic", "distance_m": 984.6, "address": "1414 NW Northrup St", "type": "doctor (dermatology)" }
        ]
      },
      "parks": {
        "score": 4.3,
        "rating": "Good",
        "notes": "Nob Hill Nature Park in the enclave; several pocket parks along NW Lovejoy and NW Northrup streets"
      },
      "education": {
        "score": 2.9,
        "rating": "Minimal",
        "count_within_1km": 2,
        "nearest": { "name": "Bridges Middle School", "distance_m": 816 },
        "options": [
          { "name": "Bridges Middle School", "distance_m": 816, "address": "1638 NW Overton St" },
          { "name": "Class Academy", "distance_m": 890, "address": "2730 NW Wardway St" }
        ]
      },
      "sports_fitness": {
        "score": 8.7,
        "rating": "Very Good",
        "count_within_1km": 11,
        "options": [
          "YogaSix", "LA Fitness", "Portland Aikikai", "Hyatt Training", "Orangetheory Fitness",
          "Kiska", "Industrial Strength Gym", "Cyclepath West (bike shop)", "Portland State University athletic facilities nearby"
        ]
      },
      "shopping": {
        "score": 8.8,
        "rating": "Very Good",
        "count_within_1km": 16,
        "notable": ["Ken's Artisan Bakery", "Title Nine (sportswear)", "Lovejoy Grocery", "Zupan's Markets"]
      },
      "services": {
        "score": 8.8,
        "rating": "Very Good",
        "notable": ["Walgreens Pharmacy (38m)", "Chase Bank (602m)", "ATM", "USPS"]
      },
      "entertainment": {
        "score": 0,
        "rating": "None in 1km",
        "notes": "No cinema, theater, or dedicated entertainment venues within 1km"
      }
    }
  },
  "transportation": {
    "public_transit": {
      "score": 9.4,
      "networks": ["TriMet", "Portland Streetcar"],
      "stops_within_1km": 8,
      "nearest_stop": {
        "name": "NW 23rd & Marshall",
        "distance_m": 128.8,
        "walk_time_min": 2,
        "routes": ["Streetcar NS Line", "A Loop", "B Loop", "Bus 8989"]
      },
      "all_stops_within_1km": [
        { "name": "NW 23rd & Marshall", "distance_m": 128, "routes": ["Streetcar", "Bus 8989"] },
        { "name": "NW Northrup & 22nd", "distance_m": 174, "routes": ["Streetcar"] },
        { "name": "NW Lovejoy & 22nd", "distance_m": 256, "routes": ["Streetcar"] },
        { "name": "NW Northrup & 21st", "distance_m": 323, "routes": ["Streetcar"] },
        { "name": "NW Lovejoy & 21st", "distance_m": 370, "routes": ["Streetcar"] },
        { "name": "NW Northrup & 18th", "distance_m": 714, "routes": ["Streetcar"] },
        { "name": "NW Lovejoy & 18th", "distance_m": 726, "routes": ["Streetcar"] }
      ]
    },
    "commute_example": {
      "destination": "Downtown Portland (SW Madison St)",
      "distance_km": 3.02,
      "modes": {
        "car": { "duration_min": 7.8, "distance_km": 3.02 },
        "foot": { "duration_min": 36, "distance_km": 3.02 },
        "bike": { "duration_min": 10, "distance_km": 3.02 }
      }
    },
    "parking": {
      "count_within_1500m": 15,
      "types": ["surface", "street_side", "multi-storey"]
    }
  },
  "amenities_summary": {
    "by_category": {
      "groceries": { "count": 3, "nearest_m": 173 },
      "restaurants": { "count": 89, "nearest_m": 42 },
      "cafes": { "count": 12, "nearest_m": 114 },
      "healthcare": { "count": 6, "nearest_m": 38 },
      "parks": { "count": "several (pocket parks)", "nearest_m": "500-800" },
      "schools": { "count": 2, "nearest_m": 816 },
      "sports_fitness": { "count": 11, "nearest_m": 400 },
      "shops": { "count": 16, "nearest_m": 242 },
      "services": { "count": "multiple", "nearest_m": 38 },
      "entertainment": { "count": 0, "nearest_m": "N/A" }
    },
    "top_5_nearest_amenities": [
      { "rank": 1, "name": "Walgreens Pharmacy", "distance_m": 38, "category": "Healthcare/Pharmacy" },
      { "rank": 2, "name": "Tara Thai Northwest", "distance_m": 42, "category": "Restaurant" },
      { "rank": 3, "name": "Top Burmese Burma Joy", "distance_m": 47, "category": "Restaurant" },
      { "rank": 4, "name": "Siri Indian Cuisine", "distance_m": 69, "category": "Restaurant" },
      { "rank": 5, "name": "Henry Higgins Boiled Bagels", "distance_m": 95, "category": "Cafe/Food" }
    ]
  },
  "limitations": [
    "No dedicated entertainment venues (cinema, theater) within 1km",
    "Educational institutions limited within 1km radius (2 schools)",
    "Grocery options limited — only 3 within 1km (convenience stores dominate)",
    "No formal parks within immediate 500m radius (Nob Hill Nature Park is farther)"
  ],
  "key_highlights": [
    "89 restaurants within 1km — one of the highest restaurant densities in Portland",
    "Walker's Paradise (10/10) — daily errands do not require a car",
    "Excellent transit — Portland Streetcar stops within 2 min walk",
    "Culinary diversity — Thai, Burmese, Indian, Greek, Mexican, Italian, Vietnamese, Korean cuisines all within 200m",
    "Nob Hill neighborhood charm with independent shops and cafes",
    "NW 23rd Ave is one of Portland's most walkable and vibrant corridors",
    "Pharmacy only 38m away — exceptional healthcare access",
    "11 sports/fitness facilities within 1km"
  ]
}
